roseau/load_flow_engine/__init__.py
roseau/load_flow_engine/cy_engine.pyi
roseau/load_flow_engine/__about__.py
roseau/load_flow_engine/cy_engine.cpython-314t-darwin.so
roseau_load_flow_engine-0.19.0.dist-info/RECORD
roseau_load_flow_engine-0.19.0.dist-info/WHEEL
roseau_load_flow_engine-0.19.0.dist-info/METADATA
roseau_load_flow_engine-0.19.0.dist-info/licenses/LICENSE.md
roseau_load_flow_engine.dylibs/libsodium.26.dylib
roseau_load_flow_engine.dylibs/libcpr.1.14.1.dylib
roseau_load_flow_engine.dylibs/libcppad_lib.2572.0.dylib
roseau_load_flow_engine.dylibs/libfmt.12.1.0.dylib
