Metadata-Version: 2.1
Name: roseau-load-flow-engine
Version: 0.19.0
Summary: Highly capable load flow solver engine (single-phase and three-phase)
Author: Victor Gouin
Author-Email: =?utf-8?q?S=C3=A9bastien_Vallet?= <sebastien.vallet@roseautechnologies.com>, Ali Hamdan <ali.hamdan@roseautechnologies.com>, =?utf-8?q?Beno=C3=AEt_Vinot?= <benoit.vinot@roseautechnologies.com>, Florent Cadoux <florent.cadoux@roseautechnologies.com>
Maintainer-Email: =?utf-8?q?S=C3=A9bastien_Vallet?= <sebastien.vallet@roseautechnologies.com>
License: Proprietary
Classifier: Development Status :: 3 - Alpha
Classifier: License :: Other/Proprietary License
Classifier: Operating System :: MacOS :: MacOS X
Classifier: Operating System :: Microsoft :: Windows
Classifier: Operating System :: POSIX :: Linux
Classifier: Programming Language :: Cython
Classifier: Programming Language :: Python :: 3.12
Classifier: Programming Language :: Python :: 3.13
Classifier: Programming Language :: Python :: 3.14
Classifier: Programming Language :: Python :: Free Threading :: 2 - Beta
Classifier: Programming Language :: Python :: Implementation :: CPython
Classifier: Topic :: Scientific/Engineering :: Physics
Project-URL: documentation, https://roseau-load-flow.roseautechnologies.com/
Project-URL: homepage, https://www.roseautechnologies.com/roseau-load-flow/
Project-URL: issues, https://github.com/RoseauTechnologies/Roseau_Load_Flow/issues/
Project-URL: repository, https://github.com/RoseauTechnologies/Roseau_Load_Flow/
Requires-Python: >=3.12
Requires-Dist: numpy>=1.21.5
